bottlejwt.py
bottlejwt-1.0.1.dist-info/METADATA
bottlejwt-1.0.1.dist-info/WHEEL
bottlejwt-1.0.1.dist-info/top_level.txt
bottlejwt-1.0.1.dist-info/RECORD
